Metadata-Version: 2.1
Name: django-twilio-2fa
Version: 0.32
Summary: Django app for performing 2FA using Twilio Verify
Home-page: https://github.com/Lenders-Cooperative/django-twilio-2fa
Author: Logan Bibby <lbibby@thesummitgrp.com>
Classifier: Programming Language :: Python :: 3
Classifier: License :: OSI Approved :: BSD License
Classifier: Operating System :: OS Independent
Requires-Python: >=3.6
License-File: LICENSE
Requires-Dist: django (>=2.2.9)
Requires-Dist: twilio (>=6.63.2)
Requires-Dist: phonenumbers (>=8.12.26)
Requires-Dist: pycountry (>=22.3.5)
Requires-Dist: djangorestframework (>=3.11.0)
